[
  {
    "fieldName": "operation",
    "type": "alphanumeric"
  },
  {
    "fieldName": "requestedat",
    "type": "date-time",
    "pattern": "dd MM yyyy hh:ass:mm"
  },
  {
    "fieldName": "completedat",
    "type": "date-time",
    "pattern": "dd MM yyyy hh:ass:mm"
  },
  {
    "fieldName": "status",
    "type": "alphabets"
  },
  {
    "fieldName": "mediaowner",
    "type": "alphabets",
    "values": [
      "Ocean Outdoor",
      "JCDecaux",
      "Global"
    ]
  },
  {
    "fieldName": "timetakeninseconds",
    "type": "number"
  }
]